README.md
setup.py
directory_analyzer/__init__.py
directory_analyzer/analyzer.py
directory_analyzer.egg-info/PKG-INFO
directory_analyzer.egg-info/SOURCES.txt
directory_analyzer.egg-info/dependency_links.txt
directory_analyzer.egg-info/top_level.txt