Metadata-Version: 2.1
Name: directory-analyzer
Version: 0.1.1
Summary: Recursive directory analyzer with stats, top files and duplicate detection
Author: Volodymyr
Author-email: vova.dzimina@gmail.com
Requires-Python: >=3.8
